sanic_graphql/__init__.py
sanic_graphql/graphqlview.py
sanic_graphql/render_graphiql.py
Sanic_GraphQL-1.2.0.dist-info/LICENSE
Sanic_GraphQL-1.2.0.dist-info/METADATA
Sanic_GraphQL-1.2.0.dist-info/WHEEL
Sanic_GraphQL-1.2.0.dist-info/top_level.txt
Sanic_GraphQL-1.2.0.dist-info/RECORD
