Metadata-Version: 2.1
Name: Sanic-GraphQL
Version: 1.2.0
Summary: Adds GraphQL support to your Sanic application
Home-page: https://github.com/graphql-python/sanic-graphql
Author: Sergey Porivaev
Author-email: porivaevs@gmail.com
License: MIT
Download-URL: https://github.com/graphql-python/sanic-graphql/releases
Keywords: api graphql protocol sanic
Platform: any
Classifier: Development Status :: 5 - Production/Stable
Classifier: Intended Audience :: Developers
Classifier: Topic :: Software Development :: Libraries
Classifier: Programming Language :: Python :: 3.6
Classifier: Programming Language :: Python :: 3.7
Classifier: Programming Language :: Python :: 3.8
Classifier: License :: OSI Approved :: MIT License
Requires-Dist: graphql-core (<3,>=2.1)
Requires-Dist: graphql-server-core (<2,>=1.1.1)
Requires-Dist: sanic (<19,>=0.5.1)
Provides-Extra: test
Requires-Dist: pytest (>=2.7.3) ; extra == 'test'
Requires-Dist: aiohttp (<4,>=3.5.0) ; extra == 'test'
Requires-Dist: yarl (<2.0,>=1.0) ; extra == 'test'
Requires-Dist: Jinja2 (>=2.10.1) ; extra == 'test'
